nano_banana_mcp/__init__.py
nano_banana_mcp/server.py
gemini_image_mcp-1.1.0.dist-info/METADATA
gemini_image_mcp-1.1.0.dist-info/WHEEL
gemini_image_mcp-1.1.0.dist-info/entry_points.txt
gemini_image_mcp-1.1.0.dist-info/licenses/LICENSE
gemini_image_mcp-1.1.0.dist-info/RECORD
