Metadata-Version: 2.4
Name: gemini-image-mcp
Version: 1.1.0
Summary: MCP server for AI-powered image generation using Google Gemini models
Project-URL: Homepage, https://channel47.dev
Project-URL: Repository, https://github.com/channel47/nano-banana-mcp
Project-URL: Documentation, https://github.com/channel47/nano-banana-mcp#readme
Project-URL: Bug Tracker, https://github.com/channel47/nano-banana-mcp/issues
Author-email: Jackson <jackson@channel47.dev>
License-Expression: MIT
License-File: LICENSE
Keywords: ai,claude,gemini,google,image-generation,mcp,model-context-protocol,nano-banana
Classifier: Development Status :: 4 - Beta
Classifier: Intended Audience :: Developers
Classifier: License :: OSI Approved :: MIT License
Classifier: Programming Language :: Python :: 3
Classifier: Programming Language :: Python :: 3.10
Classifier: Programming Language :: Python :: 3.11
Classifier: Programming Language :: Python :: 3.12
Classifier: Programming Language :: Python :: 3.13
Classifier: Topic :: Multimedia :: Graphics
Classifier: Topic :: Scientific/Engineering :: Artificial Intelligence
Requires-Python: >=3.10
Requires-Dist: fastmcp<3.0.0,>=2.14.0
Requires-Dist: httpx<1.0.0,>=0.27.1
Requires-Dist: mcp<2.0.0,>=1.23.0
Requires-Dist: pillow<12.0.0,>=10.0.0
Requires-Dist: pydantic<3.0.0,>=2.11.0
Provides-Extra: dev
Requires-Dist: mypy>=1.9.0; extra == 'dev'
Requires-Dist: pytest-asyncio>=0.23.0; extra == 'dev'
Requires-Dist: pytest-cov>=4.1.0; extra == 'dev'
Requires-Dist: pytest>=8.0.0; extra == 'dev'
Requires-Dist: ruff>=0.3.0; extra == 'dev'
